{
  "local_1000": {
    "seats": {
      "1A": { "coach": "A", "seat_number": "1", "booking_reference": null },
      "2A": { "coach": "A", "seat_number": "2", "booking_reference": null },
      "3A": { "coach": "A", "seat_number": "3", "booking_reference": null },
      "4A": { "coach": "A", "seat_number": "4", "booking_reference": null },
      "1B": { "coach": "B", "seat_number": "1", "booking_reference": null },
      "2B": { "coach": "B", "seat_number": "2", "booking_reference": null },
      "3B": { "coach": "B", "seat_number": "3", "booking_reference": null },
      "4B": { "coach": "B", "seat_number": "4", "booking_reference": null },
      "5B": { "coach": "B", "seat_number": "5", "booking_reference": null },
      "6B": { "coach": "B", "seat_number": "6", "booking_reference": null },
      "7B": { "coach": "B", "seat_number": "7", "booking_reference": null },
      "8B": { "coach": "B", "seat_number": "8", "booking_reference": null },
      "1C": { "coach": "C", "seat_number": "1", "booking_reference": null },
      "2C": { "coach": "C", "seat_number": "2", "booking_reference": null },
      "3C": { "coach": "C", "seat_number": "3", "booking_reference": null },
      "4C": { "coach": "C", "seat_number": "4", "booking_reference": null }
    }
  },
  "express_2000": {
    "seats": {
      "1A": { "coach": "A", "seat_number": "1", "booking_reference": null },
      "2A": { "coach": "A", "seat_number": "2", "booking_reference": null },
      "3A": { "coach": "A", "seat_number": "3", "booking_reference": null },
      "4A": { "coach": "A", "seat_number": "4", "booking_reference": null },
      "5A": { "coach": "A", "seat_number": "5", "booking_reference": null },
      "6A": { "coach": "A", "seat_number": "6", "booking_reference": null },
      "7A": { "coach": "A", "seat_number": "7", "booking_reference": null },
      "8A": { "coach": "A", "seat_number": "8", "booking_reference": null },
      "1B": { "coach": "B", "seat_number": "1", "booking_reference": null },
      "2B": { "coach": "B", "seat_number": "2", "booking_reference": null },
      "3B": { "coach": "B", "seat_number": "3", "booking_reference": null },
      "4B": { "coach": "B", "seat_number": "4", "booking_reference": null },
      "5B": { "coach": "B", "seat_number": "5", "booking_reference": null },
      "6B": { "coach": "B", "seat_number": "6", "booking_reference": null },
      "7B": { "coach": "B", "seat_number": "7", "booking_reference": null },
      "8B": { "coach": "B", "seat_number": "8", "booking_reference": null }
    }
  }
}
